[
  {
    "generated_at": "2026-07-20T22:02:21.763Z",
    "generated_at_kst": "2026년 7월 21일 7시 02분 21초",
    "path": "data/backups/snapshots/2026-07-20T22-02-21-763Z.json",
    "counts": {
      "time_rounds": 12,
      "time_applications": 22,
      "school_rounds": 37,
      "schools": 58,
      "school_applications": 63,
      "ensemble_rounds": 111,
      "song_applications": 163,
      "session_applications": 409,
      "manual_entries": 2
    }
  },
  {
    "generated_at": "2026-07-20T20:48:54.669Z",
    "generated_at_kst": "2026년 7월 21일 5시 48분 54초",
    "path": "data/backups/snapshots/2026-07-20T20-48-54-669Z.json",
    "counts": {
      "time_rounds": 12,
      "time_applications": 22,
      "school_rounds": 37,
      "schools": 58,
      "school_applications": 63,
      "ensemble_rounds": 111,
      "song_applications": 163,
      "session_applications": 409,
      "manual_entries": 2
    }
  },
  {
    "generated_at": "2026-07-20T19:13:57.458Z",
    "generated_at_kst": "2026년 7월 21일 4시 13분 57초",
    "path": "data/backups/snapshots/2026-07-20T19-13-57-458Z.json",
    "counts": {
      "time_rounds": 12,
      "time_applications": 22,
      "school_rounds": 37,
      "schools": 58,
      "school_applications": 63,
      "ensemble_rounds": 111,
      "song_applications": 163,
      "session_applications": 409,
      "manual_entries": 2
    }
  },
  {
    "generated_at": "2026-07-20T17:03:27.703Z",
    "generated_at_kst": "2026년 7월 21일 2시 03분 27초",
    "path": "data/backups/snapshots/2026-07-20T17-03-27-703Z.json",
    "counts": {
      "time_rounds": 12,
      "time_applications": 22,
      "school_rounds": 37,
      "schools": 58,
      "school_applications": 63,
      "ensemble_rounds": 111,
      "song_applications": 163,
      "session_applications": 409,
      "manual_entries": 2
    }
  },
  {
    "generated_at": "2026-07-20T15:29:24.141Z",
    "generated_at_kst": "2026년 7월 21일 24시 29분 24초",
    "path": "data/backups/snapshots/2026-07-20T15-29-24-141Z.json",
    "counts": {
      "time_rounds": 12,
      "time_applications": 22,
      "school_rounds": 37,
      "schools": 58,
      "school_applications": 63,
      "ensemble_rounds": 111,
      "song_applications": 163,
      "session_applications": 409,
      "manual_entries": 2
    }
  },
  {
    "generated_at": "2026-07-20T13:08:53.033Z",
    "generated_at_kst": "2026년 7월 20일 22시 08분 53초",
    "path": "data/backups/snapshots/2026-07-20T13-08-53-033Z.json",
    "counts": {
      "time_rounds": 12,
      "time_applications": 22,
      "school_rounds": 37,
      "schools": 58,
      "school_applications": 63,
      "ensemble_rounds": 111,
      "song_applications": 163,
      "session_applications": 409,
      "manual_entries": 2
    }
  },
  {
    "generated_at": "2026-07-20T10:55:05.599Z",
    "generated_at_kst": "2026년 7월 20일 19시 55분 05초",
    "path": "data/backups/snapshots/2026-07-20T10-55-05-599Z.json",
    "counts": {
      "time_rounds": 12,
      "time_applications": 22,
      "school_rounds": 37,
      "schools": 58,
      "school_applications": 63,
      "ensemble_rounds": 111,
      "song_applications": 163,
      "session_applications": 409,
      "manual_entries": 2
    }
  },
  {
    "generated_at": "2026-07-20T07:41:21.522Z",
    "generated_at_kst": "2026년 7월 20일 16시 41분 21초",
    "path": "data/backups/snapshots/2026-07-20T07-41-21-522Z.json",
    "counts": {
      "time_rounds": 12,
      "time_applications": 22,
      "school_rounds": 37,
      "schools": 58,
      "school_applications": 63,
      "ensemble_rounds": 111,
      "song_applications": 163,
      "session_applications": 409,
      "manual_entries": 2
    }
  },
  {
    "generated_at": "2026-07-20T04:22:43.169Z",
    "generated_at_kst": "2026년 7월 20일 13시 22분 43초",
    "path": "data/backups/snapshots/2026-07-20T04-22-43-169Z.json",
    "counts": {
      "time_rounds": 12,
      "time_applications": 22,
      "school_rounds": 37,
      "schools": 58,
      "school_applications": 63,
      "ensemble_rounds": 111,
      "song_applications": 163,
      "session_applications": 409,
      "manual_entries": 2
    }
  },
  {
    "generated_at": "2026-07-20T00:03:57.709Z",
    "generated_at_kst": "2026년 7월 20일 9시 03분 57초",
    "path": "data/backups/snapshots/2026-07-20T00-03-57-709Z.json",
    "counts": {
      "time_rounds": 12,
      "time_applications": 22,
      "school_rounds": 37,
      "schools": 58,
      "school_applications": 63,
      "ensemble_rounds": 111,
      "song_applications": 163,
      "session_applications": 409,
      "manual_entries": 2
    }
  },
  {
    "generated_at": "2026-07-19T22:56:52.287Z",
    "generated_at_kst": "2026년 7월 20일 7시 56분 52초",
    "path": "data/backups/snapshots/2026-07-19T22-56-52-287Z.json",
    "counts": {
      "time_rounds": 12,
      "time_applications": 22,
      "school_rounds": 37,
      "schools": 58,
      "school_applications": 63,
      "ensemble_rounds": 111,
      "song_applications": 163,
      "session_applications": 409,
      "manual_entries": 2
    }
  },
  {
    "generated_at": "2026-07-19T21:56:03.745Z",
    "generated_at_kst": "2026년 7월 20일 6시 56분 03초",
    "path": "data/backups/snapshots/2026-07-19T21-56-03-745Z.json",
    "counts": {
      "time_rounds": 12,
      "time_applications": 22,
      "school_rounds": 37,
      "schools": 58,
      "school_applications": 63,
      "ensemble_rounds": 111,
      "song_applications": 163,
      "session_applications": 409,
      "manual_entries": 2
    }
  },
  {
    "generated_at": "2026-07-19T20:53:58.691Z",
    "generated_at_kst": "2026년 7월 20일 5시 53분 58초",
    "path": "data/backups/snapshots/2026-07-19T20-53-58-691Z.json",
    "counts": {
      "time_rounds": 12,
      "time_applications": 22,
      "school_rounds": 37,
      "schools": 58,
      "school_applications": 63,
      "ensemble_rounds": 111,
      "song_applications": 163,
      "session_applications": 409,
      "manual_entries": 2
    }
  },
  {
    "generated_at": "2026-07-19T19:44:45.229Z",
    "generated_at_kst": "2026년 7월 20일 4시 44분 45초",
    "path": "data/backups/snapshots/2026-07-19T19-44-45-229Z.json",
    "counts": {
      "time_rounds": 12,
      "time_applications": 22,
      "school_rounds": 37,
      "schools": 58,
      "school_applications": 63,
      "ensemble_rounds": 111,
      "song_applications": 163,
      "session_applications": 409,
      "manual_entries": 2
    }
  },
  {
    "generated_at": "2026-07-19T18:28:19.924Z",
    "generated_at_kst": "2026년 7월 20일 3시 28분 19초",
    "path": "data/backups/snapshots/2026-07-19T18-28-19-924Z.json",
    "counts": {
      "time_rounds": 12,
      "time_applications": 22,
      "school_rounds": 37,
      "schools": 58,
      "school_applications": 63,
      "ensemble_rounds": 111,
      "song_applications": 163,
      "session_applications": 409,
      "manual_entries": 2
    }
  },
  {
    "generated_at": "2026-07-19T17:00:54.383Z",
    "generated_at_kst": "2026년 7월 20일 2시 00분 54초",
    "path": "data/backups/snapshots/2026-07-19T17-00-54-383Z.json",
    "counts": {
      "time_rounds": 12,
      "time_applications": 22,
      "school_rounds": 37,
      "schools": 58,
      "school_applications": 63,
      "ensemble_rounds": 111,
      "song_applications": 163,
      "session_applications": 409,
      "manual_entries": 2
    }
  },
  {
    "generated_at": "2026-07-19T15:31:45.039Z",
    "generated_at_kst": "2026년 7월 20일 24시 31분 45초",
    "path": "data/backups/snapshots/2026-07-19T15-31-45-039Z.json",
    "counts": {
      "time_rounds": 12,
      "time_applications": 22,
      "school_rounds": 37,
      "schools": 58,
      "school_applications": 63,
      "ensemble_rounds": 111,
      "song_applications": 163,
      "session_applications": 409,
      "manual_entries": 2
    }
  },
  {
    "generated_at": "2026-07-19T14:02:11.391Z",
    "generated_at_kst": "2026년 7월 19일 23시 02분 11초",
    "path": "data/backups/snapshots/2026-07-19T14-02-11-391Z.json",
    "counts": {
      "time_rounds": 12,
      "time_applications": 22,
      "school_rounds": 37,
      "schools": 58,
      "school_applications": 63,
      "ensemble_rounds": 111,
      "song_applications": 163,
      "session_applications": 409,
      "manual_entries": 2
    }
  },
  {
    "generated_at": "2026-07-19T12:01:54.491Z",
    "generated_at_kst": "2026년 7월 19일 21시 01분 54초",
    "path": "data/backups/snapshots/2026-07-19T12-01-54-491Z.json",
    "counts": {
      "time_rounds": 12,
      "time_applications": 22,
      "school_rounds": 37,
      "schools": 58,
      "school_applications": 63,
      "ensemble_rounds": 111,
      "song_applications": 163,
      "session_applications": 409,
      "manual_entries": 2
    }
  },
  {
    "generated_at": "2026-07-19T10:56:07.183Z",
    "generated_at_kst": "2026년 7월 19일 19시 56분 07초",
    "path": "data/backups/snapshots/2026-07-19T10-56-07-183Z.json",
    "counts": {
      "time_rounds": 12,
      "time_applications": 22,
      "school_rounds": 37,
      "schools": 58,
      "school_applications": 63,
      "ensemble_rounds": 111,
      "song_applications": 163,
      "session_applications": 409,
      "manual_entries": 2
    }
  },
  {
    "generated_at": "2026-07-19T09:29:15.474Z",
    "generated_at_kst": "2026년 7월 19일 18시 29분 15초",
    "path": "data/backups/snapshots/2026-07-19T09-29-15-474Z.json",
    "counts": {
      "time_rounds": 12,
      "time_applications": 22,
      "school_rounds": 37,
      "schools": 58,
      "school_applications": 63,
      "ensemble_rounds": 111,
      "song_applications": 163,
      "session_applications": 409,
      "manual_entries": 2
    }
  },
  {
    "generated_at": "2026-07-19T07:28:09.971Z",
    "generated_at_kst": "2026년 7월 19일 16시 28분 09초",
    "path": "data/backups/snapshots/2026-07-19T07-28-09-971Z.json",
    "counts": {
      "time_rounds": 12,
      "time_applications": 22,
      "school_rounds": 37,
      "schools": 58,
      "school_applications": 63,
      "ensemble_rounds": 111,
      "song_applications": 163,
      "session_applications": 409,
      "manual_entries": 2
    }
  },
  {
    "generated_at": "2026-07-19T04:49:35.231Z",
    "generated_at_kst": "2026년 7월 19일 13시 49분 35초",
    "path": "data/backups/snapshots/2026-07-19T04-49-35-231Z.json",
    "counts": {
      "time_rounds": 12,
      "time_applications": 22,
      "school_rounds": 37,
      "schools": 58,
      "school_applications": 63,
      "ensemble_rounds": 111,
      "song_applications": 163,
      "session_applications": 409,
      "manual_entries": 2
    }
  },
  {
    "generated_at": "2026-07-19T01:04:31.038Z",
    "generated_at_kst": "2026년 7월 19일 10시 04분 31초",
    "path": "data/backups/snapshots/2026-07-19T01-04-31-038Z.json",
    "counts": {
      "time_rounds": 12,
      "time_applications": 22,
      "school_rounds": 37,
      "schools": 58,
      "school_applications": 63,
      "ensemble_rounds": 111,
      "song_applications": 163,
      "session_applications": 409,
      "manual_entries": 2
    }
  },
  {
    "generated_at": "2026-07-18T23:27:58.476Z",
    "generated_at_kst": "2026년 7월 19일 8시 27분 58초",
    "path": "data/backups/snapshots/2026-07-18T23-27-58-476Z.json",
    "counts": {
      "time_rounds": 12,
      "time_applications": 22,
      "school_rounds": 37,
      "schools": 58,
      "school_applications": 63,
      "ensemble_rounds": 111,
      "song_applications": 163,
      "session_applications": 409,
      "manual_entries": 2
    }
  },
  {
    "generated_at": "2026-07-18T22:24:25.799Z",
    "generated_at_kst": "2026년 7월 19일 7시 24분 25초",
    "path": "data/backups/snapshots/2026-07-18T22-24-25-799Z.json",
    "counts": {
      "time_rounds": 12,
      "time_applications": 22,
      "school_rounds": 37,
      "schools": 58,
      "school_applications": 63,
      "ensemble_rounds": 111,
      "song_applications": 163,
      "session_applications": 409,
      "manual_entries": 2
    }
  },
  {
    "generated_at": "2026-07-18T21:25:04.630Z",
    "generated_at_kst": "2026년 7월 19일 6시 25분 04초",
    "path": "data/backups/snapshots/2026-07-18T21-25-04-630Z.json",
    "counts": {
      "time_rounds": 12,
      "time_applications": 22,
      "school_rounds": 37,
      "schools": 58,
      "school_applications": 63,
      "ensemble_rounds": 111,
      "song_applications": 163,
      "session_applications": 409,
      "manual_entries": 2
    }
  },
  {
    "generated_at": "2026-07-18T20:12:45.969Z",
    "generated_at_kst": "2026년 7월 19일 5시 12분 45초",
    "path": "data/backups/snapshots/2026-07-18T20-12-45-969Z.json",
    "counts": {
      "time_rounds": 12,
      "time_applications": 22,
      "school_rounds": 37,
      "schools": 58,
      "school_applications": 63,
      "ensemble_rounds": 111,
      "song_applications": 163,
      "session_applications": 409,
      "manual_entries": 2
    }
  },
  {
    "generated_at": "2026-07-18T19:09:28.151Z",
    "generated_at_kst": "2026년 7월 19일 4시 09분 28초",
    "path": "data/backups/snapshots/2026-07-18T19-09-28-151Z.json",
    "counts": {
      "time_rounds": 12,
      "time_applications": 22,
      "school_rounds": 37,
      "schools": 58,
      "school_applications": 63,
      "ensemble_rounds": 111,
      "song_applications": 163,
      "session_applications": 409,
      "manual_entries": 2
    }
  },
  {
    "generated_at": "2026-07-18T17:33:17.924Z",
    "generated_at_kst": "2026년 7월 19일 2시 33분 17초",
    "path": "data/backups/snapshots/2026-07-18T17-33-17-924Z.json",
    "counts": {
      "time_rounds": 12,
      "time_applications": 22,
      "school_rounds": 37,
      "schools": 58,
      "school_applications": 63,
      "ensemble_rounds": 111,
      "song_applications": 163,
      "session_applications": 409,
      "manual_entries": 2
    }
  },
  {
    "generated_at": "2026-07-18T16:27:27.935Z",
    "generated_at_kst": "2026년 7월 19일 1시 27분 27초",
    "path": "data/backups/snapshots/2026-07-18T16-27-27-935Z.json",
    "counts": {
      "time_rounds": 12,
      "time_applications": 22,
      "school_rounds": 37,
      "schools": 58,
      "school_applications": 63,
      "ensemble_rounds": 111,
      "song_applications": 163,
      "session_applications": 409,
      "manual_entries": 2
    }
  },
  {
    "generated_at": "2026-07-18T15:05:52.121Z",
    "generated_at_kst": "2026년 7월 19일 24시 05분 52초",
    "path": "data/backups/snapshots/2026-07-18T15-05-52-121Z.json",
    "counts": {
      "time_rounds": 12,
      "time_applications": 22,
      "school_rounds": 37,
      "schools": 58,
      "school_applications": 63,
      "ensemble_rounds": 111,
      "song_applications": 163,
      "session_applications": 409,
      "manual_entries": 2
    }
  },
  {
    "generated_at": "2026-07-18T13:59:22.157Z",
    "generated_at_kst": "2026년 7월 18일 22시 59분 22초",
    "path": "data/backups/snapshots/2026-07-18T13-59-22-157Z.json",
    "counts": {
      "time_rounds": 12,
      "time_applications": 22,
      "school_rounds": 37,
      "schools": 58,
      "school_applications": 63,
      "ensemble_rounds": 111,
      "song_applications": 163,
      "session_applications": 409,
      "manual_entries": 2
    }
  },
  {
    "generated_at": "2026-07-18T12:27:36.142Z",
    "generated_at_kst": "2026년 7월 18일 21시 27분 36초",
    "path": "data/backups/snapshots/2026-07-18T12-27-36-142Z.json",
    "counts": {
      "time_rounds": 12,
      "time_applications": 22,
      "school_rounds": 37,
      "schools": 58,
      "school_applications": 63,
      "ensemble_rounds": 111,
      "song_applications": 163,
      "session_applications": 409,
      "manual_entries": 2
    }
  },
  {
    "generated_at": "2026-07-18T11:12:13.763Z",
    "generated_at_kst": "2026년 7월 18일 20시 12분 13초",
    "path": "data/backups/snapshots/2026-07-18T11-12-13-763Z.json",
    "counts": {
      "time_rounds": 12,
      "time_applications": 22,
      "school_rounds": 37,
      "schools": 58,
      "school_applications": 63,
      "ensemble_rounds": 111,
      "song_applications": 163,
      "session_applications": 409,
      "manual_entries": 2
    }
  },
  {
    "generated_at": "2026-07-18T09:57:48.700Z",
    "generated_at_kst": "2026년 7월 18일 18시 57분 48초",
    "path": "data/backups/snapshots/2026-07-18T09-57-48-700Z.json",
    "counts": {
      "time_rounds": 12,
      "time_applications": 22,
      "school_rounds": 37,
      "schools": 58,
      "school_applications": 63,
      "ensemble_rounds": 111,
      "song_applications": 163,
      "session_applications": 409,
      "manual_entries": 2
    }
  },
  {
    "generated_at": "2026-07-18T08:23:19.216Z",
    "generated_at_kst": "2026년 7월 18일 17시 23분 19초",
    "path": "data/backups/snapshots/2026-07-18T08-23-19-216Z.json",
    "counts": {
      "time_rounds": 12,
      "time_applications": 22,
      "school_rounds": 37,
      "schools": 58,
      "school_applications": 63,
      "ensemble_rounds": 111,
      "song_applications": 163,
      "session_applications": 409,
      "manual_entries": 2
    }
  },
  {
    "generated_at": "2026-07-18T06:28:13.468Z",
    "generated_at_kst": "2026년 7월 18일 15시 28분 13초",
    "path": "data/backups/snapshots/2026-07-18T06-28-13-468Z.json",
    "counts": {
      "time_rounds": 12,
      "time_applications": 22,
      "school_rounds": 37,
      "schools": 58,
      "school_applications": 63,
      "ensemble_rounds": 111,
      "song_applications": 163,
      "session_applications": 409,
      "manual_entries": 2
    }
  },
  {
    "generated_at": "2026-07-18T04:06:19.383Z",
    "generated_at_kst": "2026년 7월 18일 13시 06분 19초",
    "path": "data/backups/snapshots/2026-07-18T04-06-19-383Z.json",
    "counts": {
      "time_rounds": 12,
      "time_applications": 22,
      "school_rounds": 37,
      "schools": 58,
      "school_applications": 63,
      "ensemble_rounds": 111,
      "song_applications": 163,
      "session_applications": 409,
      "manual_entries": 2
    }
  },
  {
    "generated_at": "2026-07-18T00:56:57.485Z",
    "generated_at_kst": "2026년 7월 18일 9시 56분 57초",
    "path": "data/backups/snapshots/2026-07-18T00-56-57-485Z.json",
    "counts": {
      "time_rounds": 12,
      "time_applications": 22,
      "school_rounds": 37,
      "schools": 58,
      "school_applications": 63,
      "ensemble_rounds": 111,
      "song_applications": 163,
      "session_applications": 409,
      "manual_entries": 2
    }
  },
  {
    "generated_at": "2026-07-17T23:25:05.968Z",
    "generated_at_kst": "2026년 7월 18일 8시 25분 05초",
    "path": "data/backups/snapshots/2026-07-17T23-25-05-968Z.json",
    "counts": {
      "time_rounds": 12,
      "time_applications": 22,
      "school_rounds": 37,
      "schools": 58,
      "school_applications": 63,
      "ensemble_rounds": 111,
      "song_applications": 163,
      "session_applications": 409,
      "manual_entries": 2
    }
  },
  {
    "generated_at": "2026-07-17T22:23:23.293Z",
    "generated_at_kst": "2026년 7월 18일 7시 23분 23초",
    "path": "data/backups/snapshots/2026-07-17T22-23-23-293Z.json",
    "counts": {
      "time_rounds": 12,
      "time_applications": 22,
      "school_rounds": 37,
      "schools": 58,
      "school_applications": 63,
      "ensemble_rounds": 111,
      "song_applications": 163,
      "session_applications": 409,
      "manual_entries": 2
    }
  },
  {
    "generated_at": "2026-07-17T21:21:51.047Z",
    "generated_at_kst": "2026년 7월 18일 6시 21분 51초",
    "path": "data/backups/snapshots/2026-07-17T21-21-51-047Z.json",
    "counts": {
      "time_rounds": 12,
      "time_applications": 22,
      "school_rounds": 37,
      "schools": 58,
      "school_applications": 63,
      "ensemble_rounds": 111,
      "song_applications": 163,
      "session_applications": 409,
      "manual_entries": 2
    }
  },
  {
    "generated_at": "2026-07-17T20:07:25.648Z",
    "generated_at_kst": "2026년 7월 18일 5시 07분 25초",
    "path": "data/backups/snapshots/2026-07-17T20-07-25-648Z.json",
    "counts": {
      "time_rounds": 12,
      "time_applications": 22,
      "school_rounds": 37,
      "schools": 58,
      "school_applications": 63,
      "ensemble_rounds": 111,
      "song_applications": 163,
      "session_applications": 409,
      "manual_entries": 2
    }
  },
  {
    "generated_at": "2026-07-17T18:34:37.312Z",
    "generated_at_kst": "2026년 7월 18일 3시 34분 37초",
    "path": "data/backups/snapshots/2026-07-17T18-34-37-312Z.json",
    "counts": {
      "time_rounds": 12,
      "time_applications": 22,
      "school_rounds": 37,
      "schools": 58,
      "school_applications": 63,
      "ensemble_rounds": 111,
      "song_applications": 163,
      "session_applications": 409,
      "manual_entries": 2
    }
  },
  {
    "generated_at": "2026-07-17T17:18:43.556Z",
    "generated_at_kst": "2026년 7월 18일 2시 18분 43초",
    "path": "data/backups/snapshots/2026-07-17T17-18-43-556Z.json",
    "counts": {
      "time_rounds": 12,
      "time_applications": 22,
      "school_rounds": 37,
      "schools": 58,
      "school_applications": 63,
      "ensemble_rounds": 111,
      "song_applications": 163,
      "session_applications": 409,
      "manual_entries": 2
    }
  },
  {
    "generated_at": "2026-07-17T15:56:50.935Z",
    "generated_at_kst": "2026년 7월 18일 24시 56분 50초",
    "path": "data/backups/snapshots/2026-07-17T15-56-50-935Z.json",
    "counts": {
      "time_rounds": 12,
      "time_applications": 22,
      "school_rounds": 37,
      "schools": 58,
      "school_applications": 63,
      "ensemble_rounds": 111,
      "song_applications": 163,
      "session_applications": 409,
      "manual_entries": 2
    }
  },
  {
    "generated_at": "2026-07-17T14:12:51.364Z",
    "generated_at_kst": "2026년 7월 17일 23시 12분 51초",
    "path": "data/backups/snapshots/2026-07-17T14-12-51-364Z.json",
    "counts": {
      "time_rounds": 12,
      "time_applications": 22,
      "school_rounds": 37,
      "schools": 58,
      "school_applications": 63,
      "ensemble_rounds": 111,
      "song_applications": 163,
      "session_applications": 409,
      "manual_entries": 2
    }
  },
  {
    "generated_at": "2026-07-17T12:11:49.390Z",
    "generated_at_kst": "2026년 7월 17일 21시 11분 49초",
    "path": "data/backups/snapshots/2026-07-17T12-11-49-390Z.json",
    "counts": {
      "time_rounds": 12,
      "time_applications": 22,
      "school_rounds": 37,
      "schools": 58,
      "school_applications": 63,
      "ensemble_rounds": 111,
      "song_applications": 163,
      "session_applications": 409,
      "manual_entries": 2
    }
  },
  {
    "generated_at": "2026-07-17T10:49:29.685Z",
    "generated_at_kst": "2026년 7월 17일 19시 49분 29초",
    "path": "data/backups/snapshots/2026-07-17T10-49-29-685Z.json",
    "counts": {
      "time_rounds": 12,
      "time_applications": 22,
      "school_rounds": 37,
      "schools": 58,
      "school_applications": 63,
      "ensemble_rounds": 111,
      "song_applications": 163,
      "session_applications": 409,
      "manual_entries": 2
    }
  },
  {
    "generated_at": "2026-07-17T08:35:49.518Z",
    "generated_at_kst": "2026년 7월 17일 17시 35분 49초",
    "path": "data/backups/snapshots/2026-07-17T08-35-49-518Z.json",
    "counts": {
      "time_rounds": 12,
      "time_applications": 22,
      "school_rounds": 37,
      "schools": 58,
      "school_applications": 63,
      "ensemble_rounds": 111,
      "song_applications": 163,
      "session_applications": 409,
      "manual_entries": 2
    }
  },
  {
    "generated_at": "2026-07-17T06:19:35.800Z",
    "generated_at_kst": "2026년 7월 17일 15시 19분 35초",
    "path": "data/backups/snapshots/2026-07-17T06-19-35-800Z.json",
    "counts": {
      "time_rounds": 12,
      "time_applications": 22,
      "school_rounds": 37,
      "schools": 58,
      "school_applications": 63,
      "ensemble_rounds": 111,
      "song_applications": 163,
      "session_applications": 409,
      "manual_entries": 2
    }
  },
  {
    "generated_at": "2026-07-17T03:47:47.044Z",
    "generated_at_kst": "2026년 7월 17일 12시 47분 47초",
    "path": "data/backups/snapshots/2026-07-17T03-47-47-044Z.json",
    "counts": {
      "time_rounds": 12,
      "time_applications": 22,
      "school_rounds": 37,
      "schools": 58,
      "school_applications": 63,
      "ensemble_rounds": 111,
      "song_applications": 163,
      "session_applications": 409,
      "manual_entries": 2
    }
  },
  {
    "generated_at": "2026-07-17T00:07:36.141Z",
    "generated_at_kst": "2026년 7월 17일 9시 07분 36초",
    "path": "data/backups/snapshots/2026-07-17T00-07-36-141Z.json",
    "counts": {
      "time_rounds": 12,
      "time_applications": 22,
      "school_rounds": 37,
      "schools": 58,
      "school_applications": 63,
      "ensemble_rounds": 111,
      "song_applications": 163,
      "session_applications": 409,
      "manual_entries": 2
    }
  },
  {
    "generated_at": "2026-07-16T22:59:18.127Z",
    "generated_at_kst": "2026년 7월 17일 7시 59분 18초",
    "path": "data/backups/snapshots/2026-07-16T22-59-18-127Z.json",
    "counts": {
      "time_rounds": 12,
      "time_applications": 22,
      "school_rounds": 37,
      "schools": 58,
      "school_applications": 63,
      "ensemble_rounds": 111,
      "song_applications": 163,
      "session_applications": 409,
      "manual_entries": 2
    }
  },
  {
    "generated_at": "2026-07-16T21:33:44.959Z",
    "generated_at_kst": "2026년 7월 17일 6시 33분 44초",
    "path": "data/backups/snapshots/2026-07-16T21-33-44-959Z.json",
    "counts": {
      "time_rounds": 12,
      "time_applications": 22,
      "school_rounds": 37,
      "schools": 58,
      "school_applications": 63,
      "ensemble_rounds": 111,
      "song_applications": 163,
      "session_applications": 409,
      "manual_entries": 2
    }
  },
  {
    "generated_at": "2026-07-16T20:04:04.694Z",
    "generated_at_kst": "2026년 7월 17일 5시 04분 04초",
    "path": "data/backups/snapshots/2026-07-16T20-04-04-694Z.json",
    "counts": {
      "time_rounds": 12,
      "time_applications": 22,
      "school_rounds": 37,
      "schools": 58,
      "school_applications": 63,
      "ensemble_rounds": 111,
      "song_applications": 163,
      "session_applications": 409,
      "manual_entries": 2
    }
  },
  {
    "generated_at": "2026-07-16T18:42:13.512Z",
    "generated_at_kst": "2026년 7월 17일 3시 42분 13초",
    "path": "data/backups/snapshots/2026-07-16T18-42-13-512Z.json",
    "counts": {
      "time_rounds": 12,
      "time_applications": 22,
      "school_rounds": 37,
      "schools": 58,
      "school_applications": 63,
      "ensemble_rounds": 111,
      "song_applications": 163,
      "session_applications": 409,
      "manual_entries": 2
    }
  },
  {
    "generated_at": "2026-07-16T17:20:42.678Z",
    "generated_at_kst": "2026년 7월 17일 2시 20분 42초",
    "path": "data/backups/snapshots/2026-07-16T17-20-42-678Z.json",
    "counts": {
      "time_rounds": 12,
      "time_applications": 22,
      "school_rounds": 37,
      "schools": 58,
      "school_applications": 63,
      "ensemble_rounds": 111,
      "song_applications": 163,
      "session_applications": 409,
      "manual_entries": 2
    }
  },
  {
    "generated_at": "2026-07-16T15:43:45.974Z",
    "generated_at_kst": "2026년 7월 17일 24시 43분 45초",
    "path": "data/backups/snapshots/2026-07-16T15-43-45-974Z.json",
    "counts": {
      "time_rounds": 12,
      "time_applications": 22,
      "school_rounds": 37,
      "schools": 58,
      "school_applications": 63,
      "ensemble_rounds": 111,
      "song_applications": 163,
      "session_applications": 409,
      "manual_entries": 2
    }
  },
  {
    "generated_at": "2026-07-16T14:00:02.931Z",
    "generated_at_kst": "2026년 7월 16일 23시 00분 02초",
    "path": "data/backups/snapshots/2026-07-16T14-00-02-931Z.json",
    "counts": {
      "time_rounds": 12,
      "time_applications": 22,
      "school_rounds": 37,
      "schools": 58,
      "school_applications": 63,
      "ensemble_rounds": 111,
      "song_applications": 163,
      "session_applications": 409,
      "manual_entries": 2
    }
  },
  {
    "generated_at": "2026-07-16T11:42:36.207Z",
    "generated_at_kst": "2026년 7월 16일 20시 42분 36초",
    "path": "data/backups/snapshots/2026-07-16T11-42-36-207Z.json",
    "counts": {
      "time_rounds": 12,
      "time_applications": 22,
      "school_rounds": 37,
      "schools": 58,
      "school_applications": 63,
      "ensemble_rounds": 111,
      "song_applications": 163,
      "session_applications": 409,
      "manual_entries": 2
    }
  },
  {
    "generated_at": "2026-07-16T09:35:33.836Z",
    "generated_at_kst": "2026년 7월 16일 18시 35분 33초",
    "path": "data/backups/snapshots/2026-07-16T09-35-33-836Z.json",
    "counts": {
      "time_rounds": 12,
      "time_applications": 22,
      "school_rounds": 37,
      "schools": 58,
      "school_applications": 63,
      "ensemble_rounds": 111,
      "song_applications": 163,
      "session_applications": 409,
      "manual_entries": 2
    }
  },
  {
    "generated_at": "2026-07-16T07:23:57.393Z",
    "generated_at_kst": "2026년 7월 16일 16시 23분 57초",
    "path": "data/backups/snapshots/2026-07-16T07-23-57-393Z.json",
    "counts": {
      "time_rounds": 12,
      "time_applications": 22,
      "school_rounds": 37,
      "schools": 58,
      "school_applications": 63,
      "ensemble_rounds": 111,
      "song_applications": 163,
      "session_applications": 409,
      "manual_entries": 2
    }
  },
  {
    "generated_at": "2026-07-16T04:39:42.479Z",
    "generated_at_kst": "2026년 7월 16일 13시 39분 42초",
    "path": "data/backups/snapshots/2026-07-16T04-39-42-479Z.json",
    "counts": {
      "time_rounds": 12,
      "time_applications": 22,
      "school_rounds": 37,
      "schools": 58,
      "school_applications": 63,
      "ensemble_rounds": 111,
      "song_applications": 163,
      "session_applications": 409,
      "manual_entries": 2
    }
  },
  {
    "generated_at": "2026-07-16T01:02:31.694Z",
    "generated_at_kst": "2026년 7월 16일 10시 02분 31초",
    "path": "data/backups/snapshots/2026-07-16T01-02-31-694Z.json",
    "counts": {
      "time_rounds": 12,
      "time_applications": 22,
      "school_rounds": 37,
      "schools": 58,
      "school_applications": 63,
      "ensemble_rounds": 111,
      "song_applications": 163,
      "session_applications": 409,
      "manual_entries": 2
    }
  },
  {
    "generated_at": "2026-07-15T23:30:06.257Z",
    "generated_at_kst": "2026년 7월 16일 8시 30분 06초",
    "path": "data/backups/snapshots/2026-07-15T23-30-06-257Z.json",
    "counts": {
      "time_rounds": 12,
      "time_applications": 22,
      "school_rounds": 37,
      "schools": 58,
      "school_applications": 63,
      "ensemble_rounds": 111,
      "song_applications": 163,
      "session_applications": 409,
      "manual_entries": 2
    }
  },
  {
    "generated_at": "2026-07-15T22:04:07.424Z",
    "generated_at_kst": "2026년 7월 16일 7시 04분 07초",
    "path": "data/backups/snapshots/2026-07-15T22-04-07-424Z.json",
    "counts": {
      "time_rounds": 12,
      "time_applications": 22,
      "school_rounds": 37,
      "schools": 58,
      "school_applications": 63,
      "ensemble_rounds": 111,
      "song_applications": 163,
      "session_applications": 409,
      "manual_entries": 2
    }
  },
  {
    "generated_at": "2026-07-15T20:34:38.419Z",
    "generated_at_kst": "2026년 7월 16일 5시 34분 38초",
    "path": "data/backups/snapshots/2026-07-15T20-34-38-419Z.json",
    "counts": {
      "time_rounds": 12,
      "time_applications": 22,
      "school_rounds": 37,
      "schools": 58,
      "school_applications": 63,
      "ensemble_rounds": 111,
      "song_applications": 163,
      "session_applications": 409,
      "manual_entries": 2
    }
  },
  {
    "generated_at": "2026-07-15T19:16:09.885Z",
    "generated_at_kst": "2026년 7월 16일 4시 16분 09초",
    "path": "data/backups/snapshots/2026-07-15T19-16-09-885Z.json",
    "counts": {
      "time_rounds": 12,
      "time_applications": 22,
      "school_rounds": 37,
      "schools": 58,
      "school_applications": 63,
      "ensemble_rounds": 111,
      "song_applications": 163,
      "session_applications": 409,
      "manual_entries": 2
    }
  },
  {
    "generated_at": "2026-07-15T17:48:27.070Z",
    "generated_at_kst": "2026년 7월 16일 2시 48분 27초",
    "path": "data/backups/snapshots/2026-07-15T17-48-27-070Z.json",
    "counts": {
      "time_rounds": 12,
      "time_applications": 22,
      "school_rounds": 37,
      "schools": 58,
      "school_applications": 63,
      "ensemble_rounds": 111,
      "song_applications": 163,
      "session_applications": 409,
      "manual_entries": 2
    }
  },
  {
    "generated_at": "2026-07-15T16:25:22.064Z",
    "generated_at_kst": "2026년 7월 16일 1시 25분 22초",
    "path": "data/backups/snapshots/2026-07-15T16-25-22-064Z.json",
    "counts": {
      "time_rounds": 12,
      "time_applications": 22,
      "school_rounds": 37,
      "schools": 58,
      "school_applications": 63,
      "ensemble_rounds": 111,
      "song_applications": 163,
      "session_applications": 409,
      "manual_entries": 2
    }
  },
  {
    "generated_at": "2026-07-15T14:54:10.289Z",
    "generated_at_kst": "2026년 7월 15일 23시 54분 10초",
    "path": "data/backups/snapshots/2026-07-15T14-54-10-289Z.json",
    "counts": {
      "time_rounds": 12,
      "time_applications": 22,
      "school_rounds": 37,
      "schools": 58,
      "school_applications": 63,
      "ensemble_rounds": 111,
      "song_applications": 163,
      "session_applications": 409,
      "manual_entries": 2
    }
  },
  {
    "generated_at": "2026-07-15T12:52:27.408Z",
    "generated_at_kst": "2026년 7월 15일 21시 52분 27초",
    "path": "data/backups/snapshots/2026-07-15T12-52-27-408Z.json",
    "counts": {
      "time_rounds": 12,
      "time_applications": 22,
      "school_rounds": 37,
      "schools": 58,
      "school_applications": 63,
      "ensemble_rounds": 111,
      "song_applications": 163,
      "session_applications": 409,
      "manual_entries": 2
    }
  },
  {
    "generated_at": "2026-07-15T11:09:37.492Z",
    "generated_at_kst": "2026년 7월 15일 20시 09분 37초",
    "path": "data/backups/snapshots/2026-07-15T11-09-37-492Z.json",
    "counts": {
      "time_rounds": 12,
      "time_applications": 22,
      "school_rounds": 37,
      "schools": 58,
      "school_applications": 63,
      "ensemble_rounds": 111,
      "song_applications": 163,
      "session_applications": 409,
      "manual_entries": 2
    }
  },
  {
    "generated_at": "2026-07-15T09:10:50.830Z",
    "generated_at_kst": "2026년 7월 15일 18시 10분 50초",
    "path": "data/backups/snapshots/2026-07-15T09-10-50-830Z.json",
    "counts": {
      "time_rounds": 12,
      "time_applications": 22,
      "school_rounds": 37,
      "schools": 58,
      "school_applications": 63,
      "ensemble_rounds": 111,
      "song_applications": 163,
      "session_applications": 409,
      "manual_entries": 2
    }
  },
  {
    "generated_at": "2026-07-15T06:36:35.305Z",
    "generated_at_kst": "2026년 7월 15일 15시 36분 35초",
    "path": "data/backups/snapshots/2026-07-15T06-36-35-305Z.json",
    "counts": {
      "time_rounds": 12,
      "time_applications": 22,
      "school_rounds": 37,
      "schools": 58,
      "school_applications": 63,
      "ensemble_rounds": 111,
      "song_applications": 163,
      "session_applications": 409,
      "manual_entries": 2
    }
  },
  {
    "generated_at": "2026-07-15T04:07:01.003Z",
    "generated_at_kst": "2026년 7월 15일 13시 07분 01초",
    "path": "data/backups/snapshots/2026-07-15T04-07-01-003Z.json",
    "counts": {
      "time_rounds": 12,
      "time_applications": 22,
      "school_rounds": 37,
      "schools": 58,
      "school_applications": 63,
      "ensemble_rounds": 111,
      "song_applications": 163,
      "session_applications": 409,
      "manual_entries": 2
    }
  },
  {
    "generated_at": "2026-07-15T00:52:21.575Z",
    "generated_at_kst": "2026년 7월 15일 9시 52분 21초",
    "path": "data/backups/snapshots/2026-07-15T00-52-21-575Z.json",
    "counts": {
      "time_rounds": 12,
      "time_applications": 22,
      "school_rounds": 37,
      "schools": 58,
      "school_applications": 63,
      "ensemble_rounds": 111,
      "song_applications": 163,
      "session_applications": 409,
      "manual_entries": 2
    }
  },
  {
    "generated_at": "2026-07-14T23:26:03.313Z",
    "generated_at_kst": "2026년 7월 15일 8시 26분 03초",
    "path": "data/backups/snapshots/2026-07-14T23-26-03-313Z.json",
    "counts": {
      "time_rounds": 12,
      "time_applications": 22,
      "school_rounds": 37,
      "schools": 58,
      "school_applications": 63,
      "ensemble_rounds": 111,
      "song_applications": 163,
      "session_applications": 409,
      "manual_entries": 2
    }
  },
  {
    "generated_at": "2026-07-14T22:00:31.185Z",
    "generated_at_kst": "2026년 7월 15일 7시 00분 31초",
    "path": "data/backups/snapshots/2026-07-14T22-00-31-185Z.json",
    "counts": {
      "time_rounds": 12,
      "time_applications": 22,
      "school_rounds": 37,
      "schools": 58,
      "school_applications": 63,
      "ensemble_rounds": 111,
      "song_applications": 163,
      "session_applications": 409,
      "manual_entries": 2
    }
  },
  {
    "generated_at": "2026-07-14T20:38:42.127Z",
    "generated_at_kst": "2026년 7월 15일 5시 38분 42초",
    "path": "data/backups/snapshots/2026-07-14T20-38-42-127Z.json",
    "counts": {
      "time_rounds": 12,
      "time_applications": 22,
      "school_rounds": 37,
      "schools": 58,
      "school_applications": 63,
      "ensemble_rounds": 111,
      "song_applications": 163,
      "session_applications": 409,
      "manual_entries": 2
    }
  },
  {
    "generated_at": "2026-07-14T19:23:45.357Z",
    "generated_at_kst": "2026년 7월 15일 4시 23분 45초",
    "path": "data/backups/snapshots/2026-07-14T19-23-45-357Z.json",
    "counts": {
      "time_rounds": 12,
      "time_applications": 22,
      "school_rounds": 37,
      "schools": 58,
      "school_applications": 63,
      "ensemble_rounds": 111,
      "song_applications": 163,
      "session_applications": 409,
      "manual_entries": 2
    }
  },
  {
    "generated_at": "2026-07-14T17:41:07.109Z",
    "generated_at_kst": "2026년 7월 15일 2시 41분 07초",
    "path": "data/backups/snapshots/2026-07-14T17-41-07-109Z.json",
    "counts": {
      "time_rounds": 12,
      "time_applications": 22,
      "school_rounds": 37,
      "schools": 58,
      "school_applications": 63,
      "ensemble_rounds": 111,
      "song_applications": 163,
      "session_applications": 409,
      "manual_entries": 2
    }
  },
  {
    "generated_at": "2026-07-14T16:18:19.578Z",
    "generated_at_kst": "2026년 7월 15일 1시 18분 19초",
    "path": "data/backups/snapshots/2026-07-14T16-18-19-578Z.json",
    "counts": {
      "time_rounds": 12,
      "time_applications": 22,
      "school_rounds": 37,
      "schools": 58,
      "school_applications": 63,
      "ensemble_rounds": 111,
      "song_applications": 163,
      "session_applications": 409,
      "manual_entries": 2
    }
  },
  {
    "generated_at": "2026-07-14T14:55:14.805Z",
    "generated_at_kst": "2026년 7월 14일 23시 55분 14초",
    "path": "data/backups/snapshots/2026-07-14T14-55-14-805Z.json",
    "counts": {
      "time_rounds": 12,
      "time_applications": 22,
      "school_rounds": 37,
      "schools": 58,
      "school_applications": 63,
      "ensemble_rounds": 111,
      "song_applications": 163,
      "session_applications": 409,
      "manual_entries": 2
    }
  },
  {
    "generated_at": "2026-07-14T12:48:19.242Z",
    "generated_at_kst": "2026년 7월 14일 21시 48분 19초",
    "path": "data/backups/snapshots/2026-07-14T12-48-19-242Z.json",
    "counts": {
      "time_rounds": 12,
      "time_applications": 22,
      "school_rounds": 37,
      "schools": 58,
      "school_applications": 63,
      "ensemble_rounds": 111,
      "song_applications": 163,
      "session_applications": 409,
      "manual_entries": 2
    }
  },
  {
    "generated_at": "2026-07-14T11:07:54.796Z",
    "generated_at_kst": "2026년 7월 14일 20시 07분 54초",
    "path": "data/backups/snapshots/2026-07-14T11-07-54-796Z.json",
    "counts": {
      "time_rounds": 12,
      "time_applications": 22,
      "school_rounds": 37,
      "schools": 58,
      "school_applications": 63,
      "ensemble_rounds": 111,
      "song_applications": 163,
      "session_applications": 409,
      "manual_entries": 2
    }
  },
  {
    "generated_at": "2026-07-14T09:06:34.647Z",
    "generated_at_kst": "2026년 7월 14일 18시 06분 34초",
    "path": "data/backups/snapshots/2026-07-14T09-06-34-647Z.json",
    "counts": {
      "time_rounds": 12,
      "time_applications": 22,
      "school_rounds": 37,
      "schools": 58,
      "school_applications": 63,
      "ensemble_rounds": 111,
      "song_applications": 163,
      "session_applications": 409,
      "manual_entries": 2
    }
  },
  {
    "generated_at": "2026-07-14T06:35:17.413Z",
    "generated_at_kst": "2026년 7월 14일 15시 35분 17초",
    "path": "data/backups/snapshots/2026-07-14T06-35-17-413Z.json",
    "counts": {
      "time_rounds": 12,
      "time_applications": 22,
      "school_rounds": 37,
      "schools": 58,
      "school_applications": 63,
      "ensemble_rounds": 111,
      "song_applications": 163,
      "session_applications": 409,
      "manual_entries": 2
    }
  },
  {
    "generated_at": "2026-07-14T04:06:29.673Z",
    "generated_at_kst": "2026년 7월 14일 13시 06분 29초",
    "path": "data/backups/snapshots/2026-07-14T04-06-29-673Z.json",
    "counts": {
      "time_rounds": 12,
      "time_applications": 22,
      "school_rounds": 37,
      "schools": 58,
      "school_applications": 63,
      "ensemble_rounds": 111,
      "song_applications": 163,
      "session_applications": 409,
      "manual_entries": 2
    }
  },
  {
    "generated_at": "2026-07-14T00:55:48.203Z",
    "generated_at_kst": "2026년 7월 14일 9시 55분 48초",
    "path": "data/backups/snapshots/2026-07-14T00-55-48-203Z.json",
    "counts": {
      "time_rounds": 12,
      "time_applications": 22,
      "school_rounds": 37,
      "schools": 58,
      "school_applications": 63,
      "ensemble_rounds": 111,
      "song_applications": 163,
      "session_applications": 409,
      "manual_entries": 2
    }
  },
  {
    "generated_at": "2026-07-13T23:28:42.134Z",
    "generated_at_kst": "2026년 7월 14일 8시 28분 42초",
    "path": "data/backups/snapshots/2026-07-13T23-28-42-134Z.json",
    "counts": {
      "time_rounds": 12,
      "time_applications": 22,
      "school_rounds": 37,
      "schools": 58,
      "school_applications": 63,
      "ensemble_rounds": 111,
      "song_applications": 163,
      "session_applications": 409,
      "manual_entries": 2
    }
  },
  {
    "generated_at": "2026-07-13T22:28:30.289Z",
    "generated_at_kst": "2026년 7월 14일 7시 28분 30초",
    "path": "data/backups/snapshots/2026-07-13T22-28-30-289Z.json",
    "counts": {
      "time_rounds": 12,
      "time_applications": 22,
      "school_rounds": 37,
      "schools": 58,
      "school_applications": 63,
      "ensemble_rounds": 111,
      "song_applications": 163,
      "session_applications": 409,
      "manual_entries": 2
    }
  }
]
